async_customerio/__init__.py
async_customerio/_config.py
async_customerio/api.py
async_customerio/client_base.py
async_customerio/constants.py
async_customerio/errors.py
async_customerio/regions.py
async_customerio/request_validator.py
async_customerio/track.py
async_customerio/utils.py
async_customerio-2.4.1.dist-info/METADATA
async_customerio-2.4.1.dist-info/WHEEL
async_customerio-2.4.1.dist-info/licenses/LICENSE
async_customerio-2.4.1.dist-info/RECORD
