Metadata-Version: 2.4
Name: async-customerio
Version: 2.4.1
Summary: Async CustomerIO Client - a Python client to interact with CustomerIO in an async fashion.
License: MIT
License-File: LICENSE
Keywords: async,asyncio,customerio,messaing,python3,data-driven-emails,push notifications,in-app messages,SMS
Author: Aleksandr Omyshev
Author-email: oomyshev@healthjoy.com
Maintainer: Healthjoy Developers
Maintainer-email: developers@healthjoy.com
Requires-Python: >=3.9,<3.14
Classifier: Development Status :: 5 - Production/Stable
Classifier: Intended Audience :: Developers
Classifier: License :: OSI Approved :: MIT License
Classifier: Natural Language :: English
Classifier: Programming Language :: Python :: 3
Classifier: Programming Language :: Python :: 3.9
Classifier: Programming Language :: Python :: 3.10
Classifier: Programming Language :: Python :: 3.11
Classifier: Programming Language :: Python :: 3.12
Classifier: Programming Language :: Python :: 3.13
Classifier: Programming Language :: Python :: 3 :: Only
Requires-Dist: h11 (>=0.16.0)
Requires-Dist: httpx[http2] (>=0.28.1,<1.0.0)
Project-URL: Repository, https://github.com/healthjoy/async-customerio
